setup.py
anjali/__init__.py
anjali.egg-info/PKG-INFO
anjali.egg-info/SOURCES.txt
anjali.egg-info/dependency_links.txt
anjali.egg-info/requires.txt
anjali.egg-info/top_level.txt